BeginnersbookShujukuxitongJiaochengChuyiFix1/README.md
BeginnersbookShujukuxitongJiaochengChuyiFix1/__init__.py
BeginnersbookShujukuxitongJiaochengChuyiFix1/__main__.py
BeginnersbookShujukuxitongJiaochengChuyiFix1/file.epub
BeginnersbookShujukuxitongJiaochengChuyiFix1/index.html
BeginnersbookShujukuxitongJiaochengChuyiFix1/css/__init__.py
BeginnersbookShujukuxitongJiaochengChuyiFix1/css/annotations.css
BeginnersbookShujukuxitongJiaochengChuyiFix1/css/main.css
BeginnersbookShujukuxitongJiaochengChuyiFix1/css/normalize.css
BeginnersbookShujukuxitongJiaochengChuyiFix1/css/popup.css
BeginnersbookShujukuxitongJiaochengChuyiFix1/font/__init__.py
BeginnersbookShujukuxitongJiaochengChuyiFix1/font/fontello.eot
BeginnersbookShujukuxitongJiaochengChuyiFix1/font/fontello.svg
BeginnersbookShujukuxitongJiaochengChuyiFix1/font/fontello.ttf
BeginnersbookShujukuxitongJiaochengChuyiFix1/font/fontello.woff
BeginnersbookShujukuxitongJiaochengChuyiFix1/img/__init__.py
BeginnersbookShujukuxitongJiaochengChuyiFix1/img/annotator-glyph-sprite.png
BeginnersbookShujukuxitongJiaochengChuyiFix1/img/annotator-icon-sprite.png
BeginnersbookShujukuxitongJiaochengChuyiFix1/img/apple-touch-icon.png
BeginnersbookShujukuxitongJiaochengChuyiFix1/img/cancelfullscreen.png
BeginnersbookShujukuxitongJiaochengChuyiFix1/img/close.png
BeginnersbookShujukuxitongJiaochengChuyiFix1/img/fullscreen.png
BeginnersbookShujukuxitongJiaochengChuyiFix1/img/loader.gif
BeginnersbookShujukuxitongJiaochengChuyiFix1/img/menu-icon.png
BeginnersbookShujukuxitongJiaochengChuyiFix1/img/save.png
BeginnersbookShujukuxitongJiaochengChuyiFix1/img/saved.png
BeginnersbookShujukuxitongJiaochengChuyiFix1/img/settings-s.png
BeginnersbookShujukuxitongJiaochengChuyiFix1/img/settings.png
BeginnersbookShujukuxitongJiaochengChuyiFix1/img/star.png
BeginnersbookShujukuxitongJiaochengChuyiFix1/js/__init__.py
BeginnersbookShujukuxitongJiaochengChuyiFix1/js/epub.js
BeginnersbookShujukuxitongJiaochengChuyiFix1/js/epub.min.js
beginnersbook_shujukuxitong_jiaocheng_chuyi_fix1-2025.3.24.0.dist-info/METADATA
beginnersbook_shujukuxitong_jiaocheng_chuyi_fix1-2025.3.24.0.dist-info/WHEEL
beginnersbook_shujukuxitong_jiaocheng_chuyi_fix1-2025.3.24.0.dist-info/entry_points.txt
beginnersbook_shujukuxitong_jiaocheng_chuyi_fix1-2025.3.24.0.dist-info/top_level.txt
beginnersbook_shujukuxitong_jiaocheng_chuyi_fix1-2025.3.24.0.dist-info/RECORD
